jupyterlab_daw/__init__.py
jupyterlab_daw/_version.py
jupyterlab_daw-0.2.1.data/data/share/jupyter/labextensions/jupyterlab-daw/package.json
jupyterlab_daw-0.2.1.data/data/share/jupyter/labextensions/jupyterlab-daw/static/234.b75bdc268b87780bafb6.js
jupyterlab_daw-0.2.1.data/data/share/jupyter/labextensions/jupyterlab-daw/static/747.023e7581a564bff7b8a0.js
jupyterlab_daw-0.2.1.data/data/share/jupyter/labextensions/jupyterlab-daw/static/885.83a6ddb332ac56c32be7.js
jupyterlab_daw-0.2.1.data/data/share/jupyter/labextensions/jupyterlab-daw/static/885.83a6ddb332ac56c32be7.js.LICENSE.txt
jupyterlab_daw-0.2.1.data/data/share/jupyter/labextensions/jupyterlab-daw/static/remoteEntry.94a2cbd7bfa31f16bfbf.js
jupyterlab_daw-0.2.1.data/data/share/jupyter/labextensions/jupyterlab-daw/static/style.js
jupyterlab_daw-0.2.1.data/data/share/jupyter/labextensions/jupyterlab-daw/static/third-party-licenses.json
jupyterlab_daw-0.2.1.data/data/share/jupyter/labextensions/jupyterlab-daw/install.json
jupyterlab_daw-0.2.1.dist-info/METADATA
jupyterlab_daw-0.2.1.dist-info/WHEEL
jupyterlab_daw-0.2.1.dist-info/licenses/LICENSE
jupyterlab_daw-0.2.1.dist-info/RECORD
