Metadata-Version: 2.1
Name: jupyterlab_daw
Version: 0.2.1
Summary: JupyterLab as a Digital Audio Workstation
Project-URL: Homepage, https://github.com/benbovy/jupyterlab-daw
Project-URL: Bug Tracker, https://github.com/benbovy/jupyterlab-daw/issues
Project-URL: Repository, https://github.com/benbovy/jupyterlab-daw.git
Author-email: Benoit Bovy <benbovy@gmail.com>
License: BSD 3-Clause License
License-File: LICENSE
Classifier: Framework :: Jupyter
Classifier: Framework :: Jupyter :: JupyterLab
Classifier: Framework :: Jupyter :: JupyterLab :: 3
Classifier: Framework :: Jupyter :: JupyterLab :: Extensions
Classifier: Framework :: Jupyter :: JupyterLab :: Extensions :: Prebuilt
Classifier: License :: OSI Approved :: BSD License
Classifier: Programming Language :: Python
Classifier: Programming Language :: Python :: 3
Classifier: Programming Language :: Python :: 3.7
Classifier: Programming Language :: Python :: 3.8
Classifier: Programming Language :: Python :: 3.9
Classifier: Programming Language :: Python :: 3.10
Classifier: Programming Language :: Python :: 3.11
Requires-Python: >=3.7
